pydts/.DS_Store
pydts/__init__.py
pydts/base_fitters.py
pydts/config.py
pydts/cross_validation.py
pydts/data_generation.py
pydts/datasets/.DS_Store
pydts/datasets/LOS_simulated_data.csv
pydts/evaluation.py
pydts/examples_utils/__init__.py
pydts/examples_utils/datasets.py
pydts/examples_utils/generate_simulations_data.py
pydts/examples_utils/mimic_consts.py
pydts/examples_utils/plots.py
pydts/examples_utils/simulations_data_config.py
pydts/fitters.py
pydts/model_selection.py
pydts/screening.py
pydts/utils.py
pydts-0.10.3.dist-info/LICENSE
pydts-0.10.3.dist-info/METADATA
pydts-0.10.3.dist-info/WHEEL
pydts-0.10.3.dist-info/RECORD
