Metadata-Version: 2.1
Name: pydts
Version: 0.10.3
Summary: Discrete time survival analysis with competing risks
Home-page: https://github.com/tomer1812/pydts
License: GNU GPLv3
Keywords: Discrete Time,Time to Event,Survival Analysis,Competing Events
Author: Tomer Meir
Author-email: tomer1812@gmail.com
Requires-Python: >=3.9,<3.14
Classifier: License :: Other/Proprietary License
Classifier: Programming Language :: Python :: 3
Classifier: Programming Language :: Python :: 3.9
Classifier: Programming Language :: Python :: 3.10
Classifier: Programming Language :: Python :: 3.11
Requires-Dist: formulaic (>=1.0)
Requires-Dist: lifelines (>=0.27)
Requires-Dist: numpy (>=1.26) ; python_version >= "3.11" and python_version < "3.14"
Requires-Dist: numpy (>=1.26,<2.1) ; python_version >= "3.9" and python_version < "3.10"
Requires-Dist: numpy (>=1.26,<2.3) ; python_version >= "3.10" and python_version < "3.11"
Requires-Dist: pandas (>=2.2.2)
Requires-Dist: psutil (>=5.9)
Requires-Dist: scikit-learn (>=1.6)
Requires-Dist: scipy (>=1.13,<1.14) ; python_version >= "3.9" and python_version < "3.10"
Requires-Dist: scipy (>=1.14,<1.16) ; python_version >= "3.10" and python_version < "3.11"
Requires-Dist: scipy (>=1.15) ; python_version >= "3.11" and python_version < "3.14"
Requires-Dist: seaborn (>=0.13)
Requires-Dist: statsmodels (>=0.14.2)
Requires-Dist: tqdm (>=4.66)
Project-URL: Documentation, https://tomer1812.github.io/pydts
Project-URL: Repository, https://github.com/tomer1812/pydts
